{
  "bins": [
    {
      "bin": "374728",
      "type": "CREDIT",
      "issuer": "BANCO DO BRASIL, S.A.",
      "countries": [
        "BR"
      ]
    },
    {
      "bin": "374729",
      "type": "CREDIT",
      "issuer": "BANCO DO BRASIL, S.A.",
      "countries": [
        "BR"
      ]
    },
    {
      "bin": "374731",
      "type": "CREDIT",
      "issuer": "BANCO DO BRASIL, S.A.",
      "countries": [
        "BR"
      ]
    },
    {
      "bin": "374732",
      "type": "CREDIT",
      "issuer": "BANCO DO BRASIL, S.A.",
      "countries": [
        "BR"
      ]
    },
    {
      "bin": "374758",
      "type": "CREDIT",
      "issuer": "BANCO BRADESCO",
      "countries": [
        "BR"
      ]
    },
    {
      "bin": "374759",
      "type": "CREDIT",
      "issuer": "BANCO BRADESCO",
      "countries": [
        "BR"
      ]
    },
    {
      "bin": "374760",
      "type": "CREDIT",
      "issuer": "BANCO BRADESCO",
      "countries": [
        "BR"
      ]
    },
    {
      "bin": "374761",
      "type": "CREDIT",
      "issuer": "BANCO BRADESCO",
      "countries": [
        "BR"
      ]
    },
    {
      "bin": "374762",
      "type": "CREDIT",
      "issuer": "BANCO BRADESCO",
      "countries": [
        "BR"
      ]
    },
    {
      "bin": "374763",
      "type": "CREDIT",
      "issuer": "BANCO BRADESCO",
      "countries": [
        "BR"
      ]
    },
    {
      "bin": "374764",
      "type": "CREDIT",
      "issuer": "BANCO BRADESCO",
      "countries": [
        "BR"
      ]
    },
    {
      "bin": "374765",
      "type": "CREDIT",
      "issuer": "BANCO BRADESCO",
      "countries": [
        "BR"
      ]
    },
    {
      "bin": "374766",
      "type": "CREDIT",
      "issuer": "BANCO BRADESCO",
      "countries": [
        "BR"
      ]
    },
    {
      "bin": "374767",
      "type": "CREDIT",
      "issuer": "BANCO BRADESCO",
      "countries": [
        "BR"
      ]
    },
    {
      "bin": "374768",
      "type": "CREDIT",
      "issuer": "BANCO BRADESCO",
      "countries": [
        "BR"
      ]
    },
    {
      "bin": "374769",
      "type": "CREDIT",
      "issuer": "BANCO BRADESCO",
      "countries": [
        "BR"
      ]
    },
    {
      "bin": "374770",
      "type": "CREDIT",
      "issuer": "BANCO BRADESCO",
      "countries": [
        "BR"
      ]
    },
    {
      "bin": "374771",
      "type": "CREDIT",
      "issuer": "BANCO BRADESCO",
      "countries": [
        "BR"
      ]
    },
    {
      "bin": "374772",
      "type": "CREDIT",
      "issuer": "BANCO BRADESCO",
      "countries": [
        "BR"
      ]
    },
    {
      "bin": "374773",
      "type": "CREDIT",
      "issuer": "BANCO BRADESCO",
      "countries": [
        "BR"
      ]
    },
    {
      "bin": "374774",
      "type": "CREDIT",
      "issuer": "BANCO BRADESCO",
      "countries": [
        "BR"
      ]
    },
    {
      "bin": "374775",
      "type": "CREDIT",
      "issuer": "BANCO BRADESCO",
      "countries": [
        "BR"
      ]
    },
    {
      "bin": "374776",
      "type": "CREDIT",
      "issuer": "BANCO BRADESCO",
      "countries": [
        "BR"
      ]
    },
    {
      "bin": "374777",
      "type": "CREDIT",
      "issuer": "BANCO BRADESCO",
      "countries": [
        "BR"
      ]
    },
    {
      "bin": "375130",
      "type": "CREDIT",
      "issuer": "BANCO BRADESCO",
      "countries": [
        "BR"
      ]
    },
    {
      "bin": "375131",
      "type": "CREDIT",
      "issuer": "BANCO BRADESCO",
      "countries": [
        "BR"
      ]
    },
    {
      "bin": "375132",
      "type": "CREDIT",
      "issuer": "BANCO BRADESCO",
      "countries": [
        "BR"
      ]
    },
    {
      "bin": "375133",
      "type": "CREDIT",
      "issuer": "BANCO BRADESCO",
      "countries": [
        "BR"
      ]
    },
    {
      "bin": "375134",
      "type": "CREDIT",
      "issuer": "BANCO BRADESCO",
      "countries": [
        "BR"
      ]
    },
    {
      "bin": "375135",
      "type": "CREDIT",
      "issuer": "BANCO BRADESCO",
      "countries": [
        "BR"
      ]
    },
    {
      "bin": "375136",
      "type": "CREDIT",
      "issuer": "BANCO BRADESCO",
      "countries": [
        "BR"
      ]
    },
    {
      "bin": "375137",
      "type": "CREDIT",
      "issuer": "BANCO BRADESCO",
      "countries": [
        "BR"
      ]
    },
    {
      "bin": "375138",
      "type": "CREDIT",
      "issuer": "BANCO BRADESCO",
      "countries": [
        "BR"
      ]
    },
    {
      "bin": "375139",
      "type": "CREDIT",
      "issuer": "BANCO BRADESCO",
      "countries": [
        "BR"
      ]
    },
    {
      "bin": "375177",
      "type": "CREDIT",
      "category": "PLATINUM",
      "issuer": "BANCO BRADESCO",
      "countries": [
        "BR"
      ]
    },
    {
      "bin": "375178",
      "type": "CREDIT",
      "category": "GOLD",
      "issuer": "BANCO BRADESCO",
      "countries": [
        "BR"
      ]
    },
    {
      "bin": "375179",
      "type": "CREDIT",
      "category": "PLATINUM",
      "issuer": "BANCO BRADESCO",
      "countries": [
        "BR"
      ]
    },
    {
      "bin": "376420",
      "type": "CREDIT",
      "category": "GREEN",
      "issuer": "BANCO BRADESCO",
      "countries": [
        "BR"
      ]
    },
    {
      "bin": "376421",
      "type": "CREDIT",
      "category": "GREEN",
      "issuer": "BANCO BRADESCO",
      "countries": [
        "BR"
      ]
    },
    {
      "bin": "376422",
      "type": "CREDIT",
      "category": "GREEN",
      "issuer": "BANCO BRADESCO",
      "countries": [
        "BR"
      ]
    },
    {
      "bin": "376423",
      "type": "CREDIT",
      "category": "GREEN",
      "issuer": "BANCO BRADESCO",
      "countries": [
        "BR"
      ]
    },
    {
      "bin": "376424",
      "type": "CREDIT",
      "category": "GREEN",
      "issuer": "BANCO BRADESCO",
      "countries": [
        "BR"
      ]
    },
    {
      "bin": "376425",
      "type": "CREDIT",
      "category": "GREEN",
      "issuer": "BANCO BRADESCO",
      "countries": [
        "BR"
      ]
    },
    {
      "bin": "376426",
      "type": "CREDIT",
      "category": "GREEN",
      "issuer": "BANCO BRADESCO",
      "countries": [
        "BR"
      ]
    },
    {
      "bin": "376427",
      "type": "CREDIT",
      "category": "GREEN",
      "issuer": "BANCO BRADESCO",
      "countries": [
        "BR"
      ]
    },
    {
      "bin": "376428",
      "type": "CREDIT",
      "category": "GREEN",
      "issuer": "BANCO BRADESCO",
      "countries": [
        "BR"
      ]
    },
    {
      "bin": "376429",
      "type": "CREDIT",
      "category": "GREEN",
      "issuer": "BANCO BRADESCO",
      "countries": [
        "BR"
      ]
    },
    {
      "bin": "376430",
      "type": "CREDIT",
      "category": "CORPORATE",
      "issuer": "BANCO BRADESCO",
      "countries": [
        "BR"
      ]
    },
    {
      "bin": "376431",
      "type": "CREDIT",
      "category": "CORPORATE",
      "issuer": "BANCO BRADESCO",
      "countries": [
        "BR"
      ]
    },
    {
      "bin": "376432",
      "type": "CREDIT",
      "category": "CORPORATE",
      "issuer": "BANCO BRADESCO",
      "countries": [
        "BR"
      ]
    },
    {
      "bin": "376433",
      "type": "CREDIT",
      "category": "CORPORATE",
      "issuer": "BANCO BRADESCO",
      "countries": [
        "BR"
      ]
    },
    {
      "bin": "376434",
      "type": "CREDIT",
      "category": "CORPORATE",
      "issuer": "BANCO BRADESCO",
      "countries": [
        "BR"
      ]
    },
    {
      "bin": "376435",
      "type": "CREDIT",
      "category": "CORPORATE",
      "issuer": "BANCO BRADESCO",
      "countries": [
        "BR"
      ]
    },
    {
      "bin": "376436",
      "type": "CREDIT",
      "category": "CORPORATE",
      "issuer": "BANCO BRADESCO",
      "countries": [
        "BR"
      ]
    },
    {
      "bin": "376437",
      "type": "CREDIT",
      "category": "CORPORATE",
      "issuer": "BANCO BRADESCO",
      "countries": [
        "BR"
      ]
    },
    {
      "bin": "376438",
      "type": "CREDIT",
      "category": "CORPORATE",
      "issuer": "BANCO BRADESCO",
      "countries": [
        "BR"
      ]
    },
    {
      "bin": "376439",
      "type": "CREDIT",
      "category": "CORPORATE",
      "issuer": "BANCO BRADESCO",
      "countries": [
        "BR"
      ]
    },
    {
      "bin": "376440",
      "type": "CREDIT",
      "category": "GOLD",
      "issuer": "BANCO BRADESCO",
      "countries": [
        "BR"
      ]
    },
    {
      "bin": "376441",
      "type": "CREDIT",
      "category": "GOLD",
      "issuer": "BANCO BRADESCO",
      "countries": [
        "BR"
      ]
    },
    {
      "bin": "376442",
      "type": "CREDIT",
      "category": "GOLD",
      "issuer": "BANCO BRADESCO",
      "countries": [
        "BR"
      ]
    },
    {
      "bin": "376443",
      "type": "CREDIT",
      "category": "GOLD",
      "issuer": "BANCO BRADESCO",
      "countries": [
        "BR"
      ]
    },
    {
      "bin": "376444",
      "type": "CREDIT",
      "category": "GOLD",
      "issuer": "BANCO BRADESCO",
      "countries": [
        "BR"
      ]
    },
    {
      "bin": "376445",
      "type": "CREDIT",
      "category": "GOLD",
      "issuer": "BANCO BRADESCO",
      "countries": [
        "BR"
      ]
    },
    {
      "bin": "376446",
      "type": "CREDIT",
      "category": "GOLD",
      "issuer": "BANCO BRADESCO",
      "countries": [
        "BR"
      ]
    },
    {
      "bin": "376447",
      "type": "CREDIT",
      "issuer": "HSBC",
      "countries": [
        "BR"
      ]
    },
    {
      "bin": "376448",
      "type": "CREDIT",
      "issuer": "HSBC",
      "countries": [
        "BR"
      ]
    },
    {
      "bin": "376449",
      "type": "CREDIT",
      "category": "PLATINUM",
      "issuer": "BANCO BRADESCO",
      "countries": [
        "BR"
      ]
    },
    {
      "bin": "376461",
      "type": "CREDIT",
      "category": "PLATINUM",
      "issuer": "BANCO BRADESCO",
      "countries": [
        "BR"
      ]
    },
    {
      "bin": "376462",
      "type": "CREDIT",
      "category": "GOLD",
      "issuer": "BANCO BRADESCO",
      "countries": [
        "BR"
      ]
    },
    {
      "bin": "376463",
      "type": "CREDIT",
      "category": "BLUE",
      "issuer": "BANCO BRADESCO",
      "countries": [
        "BR"
      ]
    },
    {
      "bin": "376464",
      "type": "CREDIT",
      "issuer": "BANCO BRADESCO",
      "countries": [
        "BR"
      ]
    },
    {
      "bin": "376465",
      "type": "CREDIT",
      "issuer": "BANCO BRADESCO",
      "countries": [
        "BR"
      ]
    },
    {
      "bin": "376466",
      "type": "CREDIT",
      "category": "BLUE",
      "issuer": "BANCO BRADESCO",
      "countries": [
        "BR"
      ]
    },
    {
      "bin": "376467",
      "type": "CREDIT",
      "issuer": "BANCO BRADESCO",
      "countries": [
        "BR"
      ]
    },
    {
      "bin": "376468",
      "type": "CREDIT",
      "countries": [
        "BR"
      ]
    },
    {
      "bin": "376469",
      "type": "CREDIT",
      "countries": [
        "BR"
      ]
    },
    {
      "bin": "376470",
      "type": "CREDIT",
      "category": "GREEN",
      "issuer": "BANCO BRADESCO",
      "countries": [
        "BR"
      ]
    },
    {
      "bin": "376471",
      "type": "CREDIT",
      "category": "GREEN",
      "issuer": "BANCO BRADESCO",
      "countries": [
        "BR"
      ]
    },
    {
      "bin": "376472",
      "type": "CREDIT",
      "category": "GREEN",
      "issuer": "BANCO BRADESCO",
      "countries": [
        "BR"
      ]
    },
    {
      "bin": "376473",
      "type": "CREDIT",
      "category": "GREEN",
      "issuer": "BANCO BRADESCO",
      "countries": [
        "BR"
      ]
    },
    {
      "bin": "376474",
      "type": "CREDIT",
      "category": "GREEN",
      "issuer": "BANCO BRADESCO",
      "countries": [
        "BR"
      ]
    },
    {
      "bin": "376475",
      "type": "CREDIT",
      "category": "GREEN",
      "issuer": "BANCO BRADESCO",
      "countries": [
        "BR"
      ]
    },
    {
      "bin": "376476",
      "type": "CREDIT",
      "category": "GREEN",
      "issuer": "BANCO BRADESCO",
      "countries": [
        "BR"
      ]
    },
    {
      "bin": "376477",
      "type": "CREDIT",
      "category": "GREEN",
      "issuer": "BANCO BRADESCO",
      "countries": [
        "BR"
      ]
    },
    {
      "bin": "376478",
      "type": "CREDIT",
      "category": "GREEN",
      "issuer": "BANCO BRADESCO",
      "countries": [
        "BR"
      ]
    },
    {
      "bin": "376479",
      "type": "CREDIT",
      "category": "GREEN",
      "issuer": "BANCO BRADESCO",
      "countries": [
        "BR"
      ]
    },
    {
      "bin": "376480",
      "type": "CREDIT",
      "issuer": "BANCO BRADESCO",
      "countries": [
        "BR"
      ]
    },
    {
      "bin": "376481",
      "type": "CREDIT",
      "issuer": "BANCO BRADESCO",
      "countries": [
        "BR"
      ]
    },
    {
      "bin": "376482",
      "type": "CREDIT",
      "issuer": "BANCO BRADESCO",
      "countries": [
        "BR"
      ]
    },
    {
      "bin": "376483",
      "type": "CREDIT",
      "issuer": "BANCO BRADESCO",
      "countries": [
        "BR"
      ]
    },
    {
      "bin": "376484",
      "type": "CREDIT",
      "issuer": "BANCO BRADESCO",
      "countries": [
        "BR"
      ]
    },
    {
      "bin": "376485",
      "type": "CREDIT",
      "issuer": "BANCO BRADESCO",
      "countries": [
        "BR"
      ]
    },
    {
      "bin": "376486",
      "type": "CREDIT",
      "issuer": "BANCO BRADESCO",
      "countries": [
        "BR"
      ]
    },
    {
      "bin": "376487",
      "type": "CREDIT",
      "issuer": "BANCO BRADESCO",
      "countries": [
        "BR"
      ]
    },
    {
      "bin": "376488",
      "type": "CREDIT",
      "issuer": "BANCO BRADESCO",
      "countries": [
        "BR"
      ]
    },
    {
      "bin": "376489",
      "type": "CREDIT",
      "issuer": "BANCO BRADESCO",
      "countries": [
        "BR"
      ]
    },
    {
      "bin": "376490",
      "type": "CREDIT",
      "issuer": "AMERICAN EXPRESS",
      "countries": [
        "BR"
      ]
    },
    {
      "bin": "376491",
      "type": "CREDIT",
      "issuer": "BANCO DO BRASIL",
      "countries": [
        "BR"
      ]
    },
    {
      "bin": "376492",
      "type": "CREDIT",
      "issuer": "BANCO DO BRASIL",
      "countries": [
        "BR"
      ]
    },
    {
      "bin": "376493",
      "type": "CREDIT",
      "issuer": "BANCO DO BRASIL",
      "countries": [
        "BR"
      ]
    },
    {
      "bin": "376494",
      "type": "CREDIT",
      "issuer": "BANCO DO BRASIL",
      "countries": [
        "BR"
      ]
    },
    {
      "bin": "376495",
      "type": "CREDIT",
      "issuer": "AMERICAN EXPRESS",
      "countries": [
        "BR"
      ]
    },
    {
      "bin": "376496",
      "type": "CREDIT",
      "issuer": "AMERICAN EXPRESS",
      "countries": [
        "BR"
      ]
    },
    {
      "bin": "376497",
      "type": "CREDIT",
      "issuer": "AMERICAN EXPRESS",
      "countries": [
        "BR"
      ]
    },
    {
      "bin": "376498",
      "type": "CREDIT",
      "issuer": "BANCO BRADESCO / VANILLA",
      "countries": [
        "BR"
      ]
    },
    {
      "bin": "376499",
      "type": "CREDIT",
      "issuer": "AMERICAN EXPRESS",
      "countries": [
        "BR"
      ]
    },
    {
      "bin": "376500",
      "type": "CREDIT",
      "issuer": "AMERICAN EXPRESS",
      "countries": [
        "BR"
      ]
    },
    {
      "bin": "376501",
      "type": "CREDIT",
      "issuer": "AMERICAN EXPRESS",
      "countries": [
        "BR"
      ]
    },
    {
      "bin": "376502",
      "type": "CREDIT",
      "issuer": "AMERICAN EXPRESS",
      "countries": [
        "BR"
      ]
    },
    {
      "bin": "376503",
      "type": "CREDIT",
      "issuer": "AMERICAN EXPRESS",
      "countries": [
        "BR"
      ]
    },
    {
      "bin": "376504",
      "type": "CREDIT",
      "issuer": "AMERICAN EXPRESS",
      "countries": [
        "BR"
      ]
    },
    {
      "bin": "376505",
      "type": "CREDIT",
      "issuer": "AMERICAN EXPRESS",
      "countries": [
        "BR"
      ]
    },
    {
      "bin": "376506",
      "type": "CREDIT",
      "issuer": "AMERICAN EXPRESS",
      "countries": [
        "BR"
      ]
    },
    {
      "bin": "376507",
      "type": "CREDIT",
      "issuer": "AMERICAN EXPRESS",
      "countries": [
        "BR"
      ]
    },
    {
      "bin": "376508",
      "type": "CREDIT",
      "issuer": "AMERICAN EXPRESS",
      "countries": [
        "BR"
      ]
    },
    {
      "bin": "376509",
      "type": "CREDIT",
      "issuer": "AMERICAN EXPRESS",
      "countries": [
        "BR"
      ]
    },
    {
      "bin": "376510",
      "type": "CREDIT",
      "issuer": "AMERICAN EXPRESS",
      "countries": [
        "BR"
      ]
    },
    {
      "bin": "376511",
      "type": "CREDIT",
      "issuer": "AMERICAN EXPRESS",
      "countries": [
        "BR"
      ]
    },
    {
      "bin": "376512",
      "type": "CREDIT",
      "issuer": "AMERICAN EXPRESS",
      "countries": [
        "BR"
      ]
    },
    {
      "bin": "376513",
      "type": "CREDIT",
      "issuer": "AMERICAN EXPRESS",
      "countries": [
        "BR"
      ]
    },
    {
      "bin": "376514",
      "type": "CREDIT",
      "issuer": "AMERICAN EXPRESS",
      "countries": [
        "BR"
      ]
    },
    {
      "bin": "376515",
      "type": "CREDIT",
      "issuer": "AMERICAN EXPRESS",
      "countries": [
        "BR"
      ]
    },
    {
      "bin": "376516",
      "type": "CREDIT",
      "issuer": "AMERICAN EXPRESS",
      "countries": [
        "BR"
      ]
    },
    {
      "bin": "376517",
      "type": "CREDIT",
      "issuer": "AMERICAN EXPRESS",
      "countries": [
        "BR"
      ]
    },
    {
      "bin": "376518",
      "type": "CREDIT",
      "issuer": "AMERICAN EXPRESS",
      "countries": [
        "BR"
      ]
    },
    {
      "bin": "376519",
      "type": "CREDIT",
      "issuer": "AMERICAN EXPRESS",
      "countries": [
        "BR"
      ]
    },
    {
      "bin": "376520",
      "type": "CREDIT",
      "issuer": "BANCO BRADESCO",
      "countries": [
        "BR"
      ]
    },
    {
      "bin": "376521",
      "type": "CREDIT",
      "issuer": "BANCO BRADESCO",
      "countries": [
        "BR"
      ]
    },
    {
      "bin": "376522",
      "type": "CREDIT",
      "issuer": "BANCO BRADESCO",
      "countries": [
        "BR"
      ]
    },
    {
      "bin": "376523",
      "type": "CREDIT",
      "issuer": "BANCO BRADESCO",
      "countries": [
        "BR"
      ]
    },
    {
      "bin": "376524",
      "type": "CREDIT",
      "issuer": "BANCO BRADESCO",
      "countries": [
        "BR"
      ]
    },
    {
      "bin": "376525",
      "type": "CREDIT",
      "issuer": "BANCO BRADESCO",
      "countries": [
        "BR"
      ]
    },
    {
      "bin": "376526",
      "type": "CREDIT",
      "issuer": "BANCO BRADESCO",
      "countries": [
        "BR"
      ]
    },
    {
      "bin": "376527",
      "type": "CREDIT",
      "issuer": "BANCO BRADESCO",
      "countries": [
        "BR"
      ]
    },
    {
      "bin": "376528",
      "type": "CREDIT",
      "issuer": "BANCO BRADESCO",
      "countries": [
        "BR"
      ]
    },
    {
      "bin": "376529",
      "type": "CREDIT",
      "issuer": "BANCO BRADESCO",
      "countries": [
        "BR"
      ]
    },
    {
      "bin": "376530",
      "type": "CREDIT",
      "issuer": "AMERICAN EXPRESS",
      "countries": [
        "BR"
      ]
    },
    {
      "bin": "376531",
      "type": "CREDIT",
      "issuer": "AMERICAN EXPRESS",
      "countries": [
        "BR"
      ]
    },
    {
      "bin": "376532",
      "type": "CREDIT",
      "issuer": "AMERICAN EXPRESS",
      "countries": [
        "BR"
      ]
    },
    {
      "bin": "376533",
      "type": "CREDIT",
      "issuer": "AMERICAN EXPRESS",
      "countries": [
        "BR"
      ]
    },
    {
      "bin": "376534",
      "type": "CREDIT",
      "issuer": "AMERICAN EXPRESS",
      "countries": [
        "BR"
      ]
    },
    {
      "bin": "376535",
      "type": "CREDIT",
      "issuer": "AMERICAN EXPRESS",
      "countries": [
        "BR"
      ]
    },
    {
      "bin": "376536",
      "type": "CREDIT",
      "issuer": "AMERICAN EXPRESS",
      "countries": [
        "BR"
      ]
    },
    {
      "bin": "376537",
      "type": "CREDIT",
      "issuer": "AMERICAN EXPRESS",
      "countries": [
        "BR"
      ]
    },
    {
      "bin": "376538",
      "type": "CREDIT",
      "issuer": "AMERICAN EXPRESS",
      "countries": [
        "BR"
      ]
    },
    {
      "bin": "376539",
      "type": "CREDIT",
      "issuer": "AMERICAN EXPRESS",
      "countries": [
        "BR"
      ]
    },
    {
      "bin": "376540",
      "type": "CREDIT",
      "issuer": "AMERICAN EXPRESS",
      "countries": [
        "BR"
      ]
    },
    {
      "bin": "376541",
      "type": "CREDIT",
      "issuer": "AMERICAN EXPRESS",
      "countries": [
        "BR"
      ]
    },
    {
      "bin": "376542",
      "type": "CREDIT",
      "issuer": "AMERICAN EXPRESS",
      "countries": [
        "BR"
      ]
    },
    {
      "bin": "376543",
      "type": "CREDIT",
      "issuer": "AMERICAN EXPRESS",
      "countries": [
        "BR"
      ]
    },
    {
      "bin": "376544",
      "type": "CREDIT",
      "issuer": "AMERICAN EXPRESS",
      "countries": [
        "BR"
      ]
    },
    {
      "bin": "376545",
      "type": "CREDIT",
      "issuer": "AMERICAN EXPRESS",
      "countries": [
        "BR"
      ]
    },
    {
      "bin": "376546",
      "type": "CREDIT",
      "issuer": "AMERICAN EXPRESS",
      "countries": [
        "BR"
      ]
    },
    {
      "bin": "376547",
      "type": "CREDIT",
      "issuer": "AMERICAN EXPRESS",
      "countries": [
        "BR"
      ]
    },
    {
      "bin": "376548",
      "type": "CREDIT",
      "issuer": "AMERICAN EXPRESS",
      "countries": [
        "BR"
      ]
    },
    {
      "bin": "376549",
      "type": "CREDIT",
      "issuer": "AMERICAN EXPRESS",
      "countries": [
        "BR"
      ]
    },
    {
      "bin": "376550",
      "type": "CREDIT",
      "countries": [
        "BR"
      ]
    },
    {
      "bin": "376551",
      "type": "CREDIT",
      "countries": [
        "BR"
      ]
    },
    {
      "bin": "376552",
      "type": "CREDIT",
      "countries": [
        "BR"
      ]
    },
    {
      "bin": "376553",
      "type": "CREDIT",
      "countries": [
        "BR"
      ]
    },
    {
      "bin": "376554",
      "type": "CREDIT",
      "countries": [
        "BR"
      ]
    },
    {
      "bin": "376600",
      "type": "CREDIT",
      "category": "CORPORATE",
      "issuer": "BANCO BRADESCO",
      "countries": [
        "BR"
      ]
    },
    {
      "bin": "376601",
      "type": "CREDIT",
      "category": "CORPORATE",
      "issuer": "BANCO BRADESCO",
      "countries": [
        "BR"
      ]
    },
    {
      "bin": "376602",
      "type": "CREDIT",
      "category": "CORPORATE",
      "issuer": "BANCO BRADESCO",
      "countries": [
        "BR"
      ]
    },
    {
      "bin": "376603",
      "type": "CREDIT",
      "category": "CORPORATE PURCHASING",
      "issuer": "BANCO BRADESCO",
      "countries": [
        "BR"
      ]
    },
    {
      "bin": "376604",
      "type": "CREDIT",
      "category": "CORPORATE PURCHASING",
      "issuer": "BANCO BRADESCO",
      "countries": [
        "BR"
      ]
    },
    {
      "bin": "376605",
      "type": "CREDIT",
      "category": "CORPORATE",
      "issuer": "BANCO BRADESCO",
      "countries": [
        "BR"
      ]
    },
    {
      "bin": "376606",
      "type": "CREDIT",
      "category": "CORPORATE",
      "issuer": "BANCO BRADESCO",
      "countries": [
        "BR"
      ]
    },
    {
      "bin": "376607",
      "type": "CREDIT",
      "category": "CORPORATE",
      "issuer": "BANCO BRADESCO",
      "countries": [
        "BR"
      ]
    },
    {
      "bin": "376608",
      "type": "CREDIT",
      "category": "CORPORATE",
      "issuer": "BANCO BRADESCO",
      "countries": [
        "BR"
      ]
    },
    {
      "bin": "376609",
      "type": "CREDIT",
      "category": "CORPORATE",
      "issuer": "BANCO BRADESCO",
      "countries": [
        "BR"
      ]
    },
    {
      "bin": "376610",
      "type": "CREDIT",
      "issuer": "AMERICAN EXPRESS",
      "countries": [
        "BR"
      ]
    },
    {
      "bin": "376611",
      "type": "CREDIT",
      "issuer": "AMERICAN EXPRESS",
      "countries": [
        "BR"
      ]
    },
    {
      "bin": "376612",
      "type": "CREDIT",
      "issuer": "AMERICAN EXPRESS",
      "countries": [
        "BR"
      ]
    },
    {
      "bin": "376613",
      "type": "CREDIT",
      "issuer": "AMERICAN EXPRESS",
      "countries": [
        "BR"
      ]
    },
    {
      "bin": "376614",
      "type": "CREDIT",
      "issuer": "AMERICAN EXPRESS",
      "countries": [
        "BR"
      ]
    },
    {
      "bin": "376615",
      "type": "CREDIT",
      "issuer": "AMERICAN EXPRESS",
      "countries": [
        "BR"
      ]
    },
    {
      "bin": "376616",
      "type": "CREDIT",
      "issuer": "HSBC",
      "countries": [
        "BR"
      ]
    },
    {
      "bin": "376617",
      "type": "CREDIT",
      "issuer": "HSBC",
      "countries": [
        "BR"
      ]
    },
    {
      "bin": "376618",
      "type": "CREDIT",
      "issuer": "HSBC",
      "countries": [
        "BR"
      ]
    },
    {
      "bin": "376619",
      "type": "CREDIT",
      "category": "PLATINUM",
      "issuer": "HSBC",
      "countries": [
        "BR"
      ]
    },
    {
      "bin": "376620",
      "type": "CREDIT",
      "issuer": "BANCO BRADESCO",
      "countries": [
        "BR"
      ]
    },
    {
      "bin": "376621",
      "type": "CREDIT",
      "issuer": "BANCO BRADESCO",
      "countries": [
        "BR"
      ]
    },
    {
      "bin": "376622",
      "type": "CREDIT",
      "issuer": "BANCO BRADESCO",
      "countries": [
        "BR"
      ]
    },
    {
      "bin": "376623",
      "type": "CREDIT",
      "category": "PLUS",
      "issuer": "BANCO BRADESCO",
      "countries": [
        "BR"
      ]
    },
    {
      "bin": "376624",
      "type": "CREDIT",
      "issuer": "BANCO BRADESCO",
      "countries": [
        "BR"
      ]
    },
    {
      "bin": "376625",
      "type": "CREDIT",
      "issuer": "BANCO BRADESCO",
      "countries": [
        "BR"
      ]
    },
    {
      "bin": "376626",
      "type": "CREDIT",
      "issuer": "BANCO BRADESCO",
      "countries": [
        "BR"
      ]
    },
    {
      "bin": "376627",
      "type": "CREDIT",
      "issuer": "BANCO BRADESCO",
      "countries": [
        "BR"
      ]
    },
    {
      "bin": "376628",
      "type": "CREDIT",
      "issuer": "BANCO BRADESCO",
      "countries": [
        "BR"
      ]
    },
    {
      "bin": "376629",
      "type": "CREDIT",
      "issuer": "BANCO BRADESCO",
      "countries": [
        "BR"
      ]
    },
    {
      "bin": "376800",
      "type": "CREDIT",
      "issuer": "AMERICAN EXPRESS COMPANY",
      "countries": [
        "BR"
      ]
    },
    {
      "bin": "376801",
      "type": "CREDIT",
      "issuer": "AMERICAN EXPRESS COMPANY",
      "countries": [
        "BR"
      ]
    },
    {
      "bin": "376802",
      "type": "CREDIT",
      "issuer": "AMERICAN EXPRESS COMPANY",
      "countries": [
        "BR"
      ]
    },
    {
      "bin": "376803",
      "type": "CREDIT",
      "issuer": "AMERICAN EXPRESS COMPANY",
      "countries": [
        "BR"
      ]
    },
    {
      "bin": "376804",
      "type": "CREDIT",
      "issuer": "AMERICAN EXPRESS COMPANY",
      "countries": [
        "BR"
      ]
    },
    {
      "bin": "376805",
      "type": "CREDIT",
      "issuer": "AMERICAN EXPRESS COMPANY",
      "countries": [
        "BR"
      ]
    },
    {
      "bin": "376806",
      "type": "CREDIT",
      "issuer": "AMERICAN EXPRESS COMPANY",
      "countries": [
        "BR"
      ]
    },
    {
      "bin": "376807",
      "type": "CREDIT",
      "issuer": "AMERICAN EXPRESS COMPANY",
      "countries": [
        "BR"
      ]
    },
    {
      "bin": "376808",
      "type": "CREDIT",
      "issuer": "AMERICAN EXPRESS COMPANY",
      "countries": [
        "BR"
      ]
    },
    {
      "bin": "376809",
      "type": "CREDIT",
      "issuer": "AMERICAN EXPRESS COMPANY",
      "countries": [
        "BR"
      ]
    },
    {
      "bin": "376810",
      "type": "CREDIT",
      "issuer": "AMERICAN EXPRESS COMPANY",
      "countries": [
        "BR"
      ]
    },
    {
      "bin": "376811",
      "type": "CREDIT",
      "issuer": "AMERICAN EXPRESS COMPANY",
      "countries": [
        "BR"
      ]
    },
    {
      "bin": "376812",
      "type": "CREDIT",
      "issuer": "AMERICAN EXPRESS COMPANY",
      "countries": [
        "BR"
      ]
    },
    {
      "bin": "376813",
      "type": "CREDIT",
      "issuer": "AMERICAN EXPRESS COMPANY",
      "countries": [
        "BR"
      ]
    },
    {
      "bin": "376814",
      "type": "CREDIT",
      "issuer": "AMERICAN EXPRESS COMPANY",
      "countries": [
        "BR"
      ]
    },
    {
      "bin": "376815",
      "type": "CREDIT",
      "issuer": "AMERICAN EXPRESS COMPANY",
      "countries": [
        "BR"
      ]
    },
    {
      "bin": "376816",
      "type": "CREDIT",
      "issuer": "AMERICAN EXPRESS COMPANY",
      "countries": [
        "BR"
      ]
    },
    {
      "bin": "376817",
      "type": "CREDIT",
      "issuer": "AMERICAN EXPRESS COMPANY",
      "countries": [
        "BR"
      ]
    },
    {
      "bin": "376818",
      "type": "CREDIT",
      "issuer": "AMERICAN EXPRESS COMPANY",
      "countries": [
        "BR"
      ]
    },
    {
      "bin": "376819",
      "type": "CREDIT",
      "issuer": "AMERICAN EXPRESS COMPANY",
      "countries": [
        "BR"
      ]
    },
    {
      "bin": "376820",
      "type": "CREDIT",
      "issuer": "AMERICAN EXPRESS COMPANY",
      "countries": [
        "BR"
      ]
    },
    {
      "bin": "376821",
      "type": "CREDIT",
      "issuer": "AMERICAN EXPRESS COMPANY",
      "countries": [
        "BR"
      ]
    },
    {
      "bin": "376822",
      "type": "CREDIT",
      "issuer": "AMERICAN EXPRESS COMPANY",
      "countries": [
        "BR"
      ]
    },
    {
      "bin": "376823",
      "type": "CREDIT",
      "issuer": "AMERICAN EXPRESS COMPANY",
      "countries": [
        "BR"
      ]
    },
    {
      "bin": "376824",
      "type": "CREDIT",
      "issuer": "AMERICAN EXPRESS COMPANY",
      "countries": [
        "BR"
      ]
    },
    {
      "bin": "376825",
      "type": "CREDIT",
      "issuer": "AMERICAN EXPRESS COMPANY",
      "countries": [
        "BR"
      ]
    },
    {
      "bin": "376826",
      "type": "CREDIT",
      "issuer": "AMERICAN EXPRESS COMPANY",
      "countries": [
        "BR"
      ]
    },
    {
      "bin": "376827",
      "type": "CREDIT",
      "issuer": "AMERICAN EXPRESS COMPANY",
      "countries": [
        "BR"
      ]
    },
    {
      "bin": "376828",
      "type": "CREDIT",
      "issuer": "AMERICAN EXPRESS COMPANY",
      "countries": [
        "BR"
      ]
    },
    {
      "bin": "376829",
      "type": "CREDIT",
      "issuer": "AMERICAN EXPRESS COMPANY",
      "countries": [
        "BR"
      ]
    },
    {
      "bin": "376830",
      "type": "CREDIT",
      "issuer": "AMERICAN EXPRESS COMPANY",
      "countries": [
        "BR"
      ]
    },
    {
      "bin": "376831",
      "type": "CREDIT",
      "issuer": "AMERICAN EXPRESS COMPANY",
      "countries": [
        "BR"
      ]
    },
    {
      "bin": "376832",
      "type": "CREDIT",
      "issuer": "AMERICAN EXPRESS COMPANY",
      "countries": [
        "BR"
      ]
    },
    {
      "bin": "376833",
      "type": "CREDIT",
      "issuer": "AMERICAN EXPRESS COMPANY",
      "countries": [
        "BR"
      ]
    },
    {
      "bin": "376834",
      "type": "CREDIT",
      "issuer": "AMERICAN EXPRESS COMPANY",
      "countries": [
        "BR"
      ]
    },
    {
      "bin": "376835",
      "type": "CREDIT",
      "issuer": "AMERICAN EXPRESS COMPANY",
      "countries": [
        "BR"
      ]
    },
    {
      "bin": "376836",
      "type": "CREDIT",
      "issuer": "AMERICAN EXPRESS COMPANY",
      "countries": [
        "BR"
      ]
    },
    {
      "bin": "376837",
      "type": "CREDIT",
      "issuer": "AMERICAN EXPRESS COMPANY",
      "countries": [
        "BR"
      ]
    },
    {
      "bin": "376838",
      "type": "CREDIT",
      "issuer": "AMERICAN EXPRESS COMPANY",
      "countries": [
        "BR"
      ]
    },
    {
      "bin": "376839",
      "type": "CREDIT",
      "issuer": "AMERICAN EXPRESS COMPANY",
      "countries": [
        "BR"
      ]
    },
    {
      "bin": "376840",
      "type": "CREDIT",
      "issuer": "AMERICAN EXPRESS COMPANY",
      "countries": [
        "BR"
      ]
    },
    {
      "bin": "376841",
      "type": "CREDIT",
      "issuer": "AMERICAN EXPRESS COMPANY",
      "countries": [
        "BR"
      ]
    },
    {
      "bin": "376842",
      "type": "CREDIT",
      "issuer": "AMERICAN EXPRESS COMPANY",
      "countries": [
        "BR"
      ]
    },
    {
      "bin": "376843",
      "type": "CREDIT",
      "issuer": "AMERICAN EXPRESS COMPANY",
      "countries": [
        "BR"
      ]
    },
    {
      "bin": "376844",
      "type": "CREDIT",
      "issuer": "AMERICAN EXPRESS COMPANY",
      "countries": [
        "BR"
      ]
    },
    {
      "bin": "376845",
      "type": "CREDIT",
      "issuer": "AMERICAN EXPRESS COMPANY",
      "countries": [
        "BR"
      ]
    },
    {
      "bin": "376846",
      "type": "CREDIT",
      "issuer": "AMERICAN EXPRESS COMPANY",
      "countries": [
        "BR"
      ]
    },
    {
      "bin": "376847",
      "type": "CREDIT",
      "issuer": "AMERICAN EXPRESS COMPANY",
      "countries": [
        "BR"
      ]
    },
    {
      "bin": "376848",
      "type": "CREDIT",
      "issuer": "AMERICAN EXPRESS COMPANY",
      "countries": [
        "BR"
      ]
    },
    {
      "bin": "376849",
      "type": "CREDIT",
      "issuer": "AMERICAN EXPRESS COMPANY",
      "countries": [
        "BR"
      ]
    },
    {
      "bin": "376850",
      "type": "CREDIT",
      "issuer": "AMERICAN EXPRESS COMPANY",
      "countries": [
        "BR"
      ]
    },
    {
      "bin": "376851",
      "type": "CREDIT",
      "issuer": "AMERICAN EXPRESS COMPANY",
      "countries": [
        "BR"
      ]
    },
    {
      "bin": "376852",
      "type": "CREDIT",
      "issuer": "AMERICAN EXPRESS COMPANY",
      "countries": [
        "BR"
      ]
    },
    {
      "bin": "376853",
      "type": "CREDIT",
      "issuer": "AMERICAN EXPRESS COMPANY",
      "countries": [
        "BR"
      ]
    },
    {
      "bin": "376854",
      "type": "CREDIT",
      "issuer": "AMERICAN EXPRESS COMPANY",
      "countries": [
        "BR"
      ]
    },
    {
      "bin": "376855",
      "type": "CREDIT",
      "issuer": "AMERICAN EXPRESS COMPANY",
      "countries": [
        "BR"
      ]
    },
    {
      "bin": "376856",
      "type": "CREDIT",
      "issuer": "AMERICAN EXPRESS COMPANY",
      "countries": [
        "BR"
      ]
    },
    {
      "bin": "376857",
      "type": "CREDIT",
      "issuer": "AMERICAN EXPRESS COMPANY",
      "countries": [
        "BR"
      ]
    },
    {
      "bin": "376858",
      "type": "CREDIT",
      "issuer": "AMERICAN EXPRESS COMPANY",
      "countries": [
        "BR"
      ]
    },
    {
      "bin": "376859",
      "type": "CREDIT",
      "issuer": "AMERICAN EXPRESS COMPANY",
      "countries": [
        "BR"
      ]
    },
    {
      "bin": "376860",
      "type": "CREDIT",
      "issuer": "AMERICAN EXPRESS COMPANY",
      "countries": [
        "BR"
      ]
    },
    {
      "bin": "376861",
      "type": "CREDIT",
      "issuer": "AMERICAN EXPRESS COMPANY",
      "countries": [
        "BR"
      ]
    },
    {
      "bin": "376863",
      "type": "CREDIT",
      "issuer": "AMERICAN EXPRESS COMPANY",
      "countries": [
        "BR"
      ]
    },
    {
      "bin": "376864",
      "type": "CREDIT",
      "issuer": "AMERICAN EXPRESS COMPANY",
      "countries": [
        "BR"
      ]
    },
    {
      "bin": "376865",
      "type": "CREDIT",
      "issuer": "AMERICAN EXPRESS COMPANY",
      "countries": [
        "BR"
      ]
    },
    {
      "bin": "376866",
      "type": "CREDIT",
      "issuer": "AMERICAN EXPRESS COMPANY",
      "countries": [
        "BR"
      ]
    },
    {
      "bin": "376867",
      "type": "CREDIT",
      "issuer": "AMERICAN EXPRESS COMPANY",
      "countries": [
        "BR"
      ]
    },
    {
      "bin": "376868",
      "type": "CREDIT",
      "issuer": "AMERICAN EXPRESS COMPANY",
      "countries": [
        "BR"
      ]
    },
    {
      "bin": "376869",
      "type": "CREDIT",
      "issuer": "AMERICAN EXPRESS COMPANY",
      "countries": [
        "BR"
      ]
    },
    {
      "bin": "376870",
      "type": "CREDIT",
      "issuer": "AMERICAN EXPRESS COMPANY",
      "countries": [
        "BR"
      ]
    },
    {
      "bin": "376871",
      "type": "CREDIT",
      "issuer": "AMERICAN EXPRESS COMPANY",
      "countries": [
        "BR"
      ]
    },
    {
      "bin": "376872",
      "type": "CREDIT",
      "issuer": "AMERICAN EXPRESS COMPANY",
      "countries": [
        "BR"
      ]
    },
    {
      "bin": "376873",
      "type": "CREDIT",
      "issuer": "AMERICAN EXPRESS COMPANY",
      "countries": [
        "BR"
      ]
    },
    {
      "bin": "376874",
      "type": "CREDIT",
      "issuer": "AMERICAN EXPRESS COMPANY",
      "countries": [
        "BR"
      ]
    },
    {
      "bin": "376875",
      "type": "CREDIT",
      "issuer": "AMERICAN EXPRESS COMPANY",
      "countries": [
        "BR"
      ]
    },
    {
      "bin": "376876",
      "type": "CREDIT",
      "issuer": "AMERICAN EXPRESS COMPANY",
      "countries": [
        "BR"
      ]
    },
    {
      "bin": "376877",
      "type": "CREDIT",
      "issuer": "AMERICAN EXPRESS COMPANY",
      "countries": [
        "BR"
      ]
    },
    {
      "bin": "376878",
      "type": "CREDIT",
      "issuer": "AMERICAN EXPRESS COMPANY",
      "countries": [
        "BR"
      ]
    },
    {
      "bin": "376879",
      "type": "CREDIT",
      "issuer": "AMERICAN EXPRESS COMPANY",
      "countries": [
        "BR"
      ]
    },
    {
      "bin": "376880",
      "type": "CREDIT",
      "issuer": "AMERICAN EXPRESS COMPANY",
      "countries": [
        "BR"
      ]
    },
    {
      "bin": "376881",
      "type": "CREDIT",
      "issuer": "AMERICAN EXPRESS COMPANY",
      "countries": [
        "BR"
      ]
    },
    {
      "bin": "376882",
      "type": "CREDIT",
      "issuer": "AMERICAN EXPRESS COMPANY",
      "countries": [
        "BR"
      ]
    },
    {
      "bin": "376883",
      "type": "CREDIT",
      "issuer": "AMERICAN EXPRESS COMPANY",
      "countries": [
        "BR"
      ]
    },
    {
      "bin": "376884",
      "type": "CREDIT",
      "issuer": "AMERICAN EXPRESS COMPANY",
      "countries": [
        "BR"
      ]
    },
    {
      "bin": "376885",
      "type": "CREDIT",
      "issuer": "AMERICAN EXPRESS COMPANY",
      "countries": [
        "BR"
      ]
    },
    {
      "bin": "376886",
      "type": "CREDIT",
      "issuer": "AMERICAN EXPRESS COMPANY",
      "countries": [
        "BR"
      ]
    },
    {
      "bin": "376887",
      "type": "CREDIT",
      "issuer": "AMERICAN EXPRESS COMPANY",
      "countries": [
        "BR"
      ]
    },
    {
      "bin": "376888",
      "type": "CREDIT",
      "issuer": "AMERICAN EXPRESS COMPANY",
      "countries": [
        "BR"
      ]
    },
    {
      "bin": "376889",
      "type": "CREDIT",
      "issuer": "AMERICAN EXPRESS COMPANY",
      "countries": [
        "BR"
      ]
    },
    {
      "bin": "376890",
      "type": "CREDIT",
      "issuer": "AMERICAN EXPRESS COMPANY",
      "countries": [
        "BR"
      ]
    },
    {
      "bin": "376891",
      "type": "CREDIT",
      "issuer": "AMERICAN EXPRESS COMPANY",
      "countries": [
        "BR"
      ]
    },
    {
      "bin": "376892",
      "type": "CREDIT",
      "issuer": "AMERICAN EXPRESS COMPANY",
      "countries": [
        "BR"
      ]
    },
    {
      "bin": "376893",
      "type": "CREDIT",
      "issuer": "AMERICAN EXPRESS COMPANY",
      "countries": [
        "BR"
      ]
    },
    {
      "bin": "376894",
      "type": "CREDIT",
      "issuer": "AMERICAN EXPRESS COMPANY",
      "countries": [
        "BR"
      ]
    },
    {
      "bin": "376895",
      "type": "CREDIT",
      "issuer": "AMERICAN EXPRESS COMPANY",
      "countries": [
        "BR"
      ]
    },
    {
      "bin": "376896",
      "type": "CREDIT",
      "issuer": "AMERICAN EXPRESS COMPANY",
      "countries": [
        "BR"
      ]
    },
    {
      "bin": "376897",
      "type": "CREDIT",
      "issuer": "AMERICAN EXPRESS COMPANY",
      "countries": [
        "BR"
      ]
    },
    {
      "bin": "376898",
      "type": "CREDIT",
      "issuer": "AMERICAN EXPRESS COMPANY",
      "countries": [
        "BR"
      ]
    },
    {
      "bin": "376899",
      "type": "CREDIT",
      "issuer": "AMERICAN EXPRESS COMPANY",
      "countries": [
        "BR"
      ]
    },
    {
      "bin": "377169",
      "type": "CREDIT",
      "category": "PLATINUM",
      "issuer": "BANCO BRADESCO",
      "countries": [
        "BR"
      ]
    },
    {
      "bin": "377174",
      "type": "CREDIT",
      "category": "PLATINUM",
      "issuer": "BANCO BRADESCO",
      "countries": [
        "BR"
      ]
    }
  ]
}
