{
  "bins": [
    {
      "bin": "376343",
      "type": "CREDIT",
      "category": "CLASSIC",
      "issuer": "CATHAY PACIFIC",
      "countries": [
        "TW"
      ]
    },
    {
      "bin": "376346",
      "type": "CREDIT",
      "category": "GOLD",
      "issuer": "AMERICAN EXPRESS TAIWAN",
      "countries": [
        "TW"
      ]
    },
    {
      "bin": "376347",
      "type": "CREDIT",
      "countries": [
        "TW"
      ]
    },
    {
      "bin": "376348",
      "type": "CREDIT",
      "countries": [
        "TW"
      ]
    },
    {
      "bin": "376349",
      "type": "CREDIT",
      "countries": [
        "TW"
      ]
    },
    {
      "bin": "376350",
      "type": "CREDIT",
      "countries": [
        "TW"
      ]
    },
    {
      "bin": "376351",
      "type": "CREDIT",
      "countries": [
        "TW"
      ]
    },
    {
      "bin": "376352",
      "type": "CREDIT",
      "countries": [
        "TW"
      ]
    },
    {
      "bin": "376353",
      "type": "CREDIT",
      "countries": [
        "TW"
      ]
    },
    {
      "bin": "376354",
      "type": "CREDIT",
      "countries": [
        "TW"
      ]
    },
    {
      "bin": "376355",
      "type": "CREDIT",
      "countries": [
        "TW"
      ]
    },
    {
      "bin": "376356",
      "type": "CREDIT",
      "countries": [
        "TW"
      ]
    },
    {
      "bin": "376357",
      "type": "CREDIT",
      "category": "PLATINUM",
      "issuer": "AMERICAN EXPRESS TAIWAN",
      "countries": [
        "TW"
      ]
    },
    {
      "bin": "376359",
      "type": "CREDIT",
      "category": "CORPORATE",
      "issuer": "AMERICAN EXPRESS TAIWAN",
      "countries": [
        "TW"
      ]
    }
  ]
}
