{
  "bins": [
    {
      "bin": "370105",
      "type": "CREDIT",
      "issuer": "AMERICAN EXPRESS",
      "countries": [
        "BE"
      ]
    },
    {
      "bin": "370106",
      "type": "CREDIT",
      "issuer": "AMERICAN EXPRESS",
      "countries": [
        "BE"
      ]
    },
    {
      "bin": "370107",
      "type": "CREDIT",
      "issuer": "AMERICAN EXPRESS",
      "countries": [
        "BE"
      ]
    },
    {
      "bin": "370108",
      "type": "CREDIT",
      "issuer": "AMERICAN EXPRESS",
      "countries": [
        "BE"
      ]
    },
    {
      "bin": "370109",
      "type": "CREDIT",
      "issuer": "AMERICAN EXPRESS",
      "countries": [
        "BE"
      ]
    },
    {
      "bin": "374100",
      "type": "CREDIT",
      "issuer": "AMERICAN EXPRESS",
      "countries": [
        "BE"
      ]
    },
    {
      "bin": "374101",
      "type": "CREDIT",
      "issuer": "AMERICAN EXPRESS",
      "countries": [
        "BE"
      ]
    },
    {
      "bin": "374102",
      "type": "CREDIT",
      "issuer": "AMERICAN EXPRESS",
      "countries": [
        "BE"
      ]
    },
    {
      "bin": "374103",
      "type": "CREDIT",
      "issuer": "AMERICAN EXPRESS",
      "countries": [
        "BE"
      ]
    },
    {
      "bin": "374104",
      "type": "CREDIT",
      "issuer": "AMERICAN EXPRESS",
      "countries": [
        "BE"
      ]
    },
    {
      "bin": "374105",
      "type": "CREDIT",
      "issuer": "AMERICAN EXPRESS",
      "countries": [
        "BE"
      ]
    },
    {
      "bin": "374106",
      "type": "CREDIT",
      "issuer": "AMERICAN EXPRESS",
      "countries": [
        "BE"
      ]
    },
    {
      "bin": "374107",
      "type": "CREDIT",
      "issuer": "AMERICAN EXPRESS",
      "countries": [
        "BE"
      ]
    },
    {
      "bin": "374108",
      "type": "CREDIT",
      "issuer": "AMERICAN EXPRESS",
      "countries": [
        "BE"
      ]
    },
    {
      "bin": "374109",
      "type": "CREDIT",
      "issuer": "AMERICAN EXPRESS",
      "countries": [
        "BE"
      ]
    },
    {
      "bin": "374110",
      "type": "CREDIT",
      "issuer": "AMERICAN EXPRESS",
      "countries": [
        "BE"
      ]
    },
    {
      "bin": "374111",
      "type": "CREDIT",
      "issuer": "AMERICAN EXPRESS",
      "countries": [
        "BE"
      ]
    },
    {
      "bin": "374112",
      "type": "CREDIT",
      "issuer": "AMERICAN EXPRESS",
      "countries": [
        "BE"
      ]
    },
    {
      "bin": "374113",
      "type": "CREDIT",
      "issuer": "AMERICAN EXPRESS",
      "countries": [
        "BE"
      ]
    },
    {
      "bin": "374114",
      "type": "CREDIT",
      "issuer": "AMERICAN EXPRESS",
      "countries": [
        "BE"
      ]
    },
    {
      "bin": "374115",
      "type": "CREDIT",
      "issuer": "AMERICAN EXPRESS",
      "countries": [
        "BE"
      ]
    },
    {
      "bin": "374116",
      "type": "CREDIT",
      "issuer": "AMERICAN EXPRESS",
      "countries": [
        "BE"
      ]
    },
    {
      "bin": "374117",
      "type": "CREDIT",
      "issuer": "AMERICAN EXPRESS",
      "countries": [
        "BE"
      ]
    },
    {
      "bin": "374118",
      "type": "CREDIT",
      "issuer": "AMERICAN EXPRESS",
      "countries": [
        "BE"
      ]
    },
    {
      "bin": "374119",
      "type": "CREDIT",
      "issuer": "AMERICAN EXPRESS",
      "countries": [
        "BE"
      ]
    },
    {
      "bin": "374120",
      "type": "CREDIT",
      "issuer": "AMERICAN EXPRESS",
      "countries": [
        "BE"
      ]
    },
    {
      "bin": "374121",
      "type": "CREDIT",
      "issuer": "AMERICAN EXPRESS",
      "countries": [
        "BE"
      ]
    },
    {
      "bin": "374122",
      "type": "CREDIT",
      "issuer": "AMERICAN EXPRESS",
      "countries": [
        "BE"
      ]
    },
    {
      "bin": "374123",
      "type": "CREDIT",
      "issuer": "AMERICAN EXPRESS",
      "countries": [
        "BE"
      ]
    },
    {
      "bin": "374124",
      "type": "CREDIT",
      "issuer": "AMERICAN EXPRESS",
      "countries": [
        "BE"
      ]
    },
    {
      "bin": "374125",
      "type": "CREDIT",
      "issuer": "AMERICAN EXPRESS",
      "countries": [
        "BE"
      ]
    },
    {
      "bin": "374126",
      "type": "CREDIT",
      "issuer": "AMERICAN EXPRESS",
      "countries": [
        "BE"
      ]
    },
    {
      "bin": "374127",
      "type": "CREDIT",
      "issuer": "AMERICAN EXPRESS",
      "countries": [
        "BE"
      ]
    },
    {
      "bin": "374128",
      "type": "CREDIT",
      "issuer": "AMERICAN EXPRESS",
      "countries": [
        "BE"
      ]
    },
    {
      "bin": "374129",
      "type": "CREDIT",
      "issuer": "AMERICAN EXPRESS",
      "countries": [
        "BE"
      ]
    },
    {
      "bin": "374130",
      "type": "CREDIT",
      "issuer": "AMERICAN EXPRESS",
      "countries": [
        "BE"
      ]
    },
    {
      "bin": "374131",
      "type": "CREDIT",
      "issuer": "AMERICAN EXPRESS",
      "countries": [
        "BE"
      ]
    },
    {
      "bin": "374132",
      "type": "CREDIT",
      "issuer": "AMERICAN EXPRESS",
      "countries": [
        "BE"
      ]
    },
    {
      "bin": "374133",
      "type": "CREDIT",
      "issuer": "AMERICAN EXPRESS",
      "countries": [
        "BE"
      ]
    },
    {
      "bin": "374134",
      "type": "CREDIT",
      "issuer": "AMERICAN EXPRESS",
      "countries": [
        "BE"
      ]
    },
    {
      "bin": "374135",
      "type": "CREDIT",
      "issuer": "AMERICAN EXPRESS",
      "countries": [
        "BE"
      ]
    },
    {
      "bin": "374136",
      "type": "CREDIT",
      "issuer": "AMERICAN EXPRESS",
      "countries": [
        "BE"
      ]
    },
    {
      "bin": "374137",
      "type": "CREDIT",
      "issuer": "AMERICAN EXPRESS",
      "countries": [
        "BE"
      ]
    },
    {
      "bin": "374138",
      "type": "CREDIT",
      "issuer": "AMERICAN EXPRESS",
      "countries": [
        "BE"
      ]
    },
    {
      "bin": "374139",
      "type": "CREDIT",
      "issuer": "AMERICAN EXPRESS",
      "countries": [
        "BE"
      ]
    },
    {
      "bin": "374140",
      "type": "CREDIT",
      "issuer": "AMERICAN EXPRESS",
      "countries": [
        "BE"
      ]
    },
    {
      "bin": "374141",
      "type": "CREDIT",
      "issuer": "AMERICAN EXPRESS",
      "countries": [
        "BE"
      ]
    },
    {
      "bin": "374142",
      "type": "CREDIT",
      "issuer": "AMERICAN EXPRESS",
      "countries": [
        "BE"
      ]
    },
    {
      "bin": "374143",
      "type": "CREDIT",
      "issuer": "AMERICAN EXPRESS",
      "countries": [
        "BE"
      ]
    },
    {
      "bin": "374144",
      "type": "CREDIT",
      "issuer": "AMERICAN EXPRESS",
      "countries": [
        "BE"
      ]
    },
    {
      "bin": "374145",
      "type": "CREDIT",
      "issuer": "AMERICAN EXPRESS",
      "countries": [
        "BE"
      ]
    },
    {
      "bin": "374146",
      "type": "CREDIT",
      "issuer": "AMERICAN EXPRESS",
      "countries": [
        "BE"
      ]
    },
    {
      "bin": "374147",
      "type": "CREDIT",
      "issuer": "AMERICAN EXPRESS",
      "countries": [
        "BE"
      ]
    },
    {
      "bin": "374148",
      "type": "CREDIT",
      "issuer": "AMERICAN EXPRESS",
      "countries": [
        "BE"
      ]
    },
    {
      "bin": "374149",
      "type": "CREDIT",
      "issuer": "AMERICAN EXPRESS",
      "countries": [
        "BE"
      ]
    },
    {
      "bin": "374150",
      "type": "CREDIT",
      "issuer": "AMERICAN EXPRESS",
      "countries": [
        "BE"
      ]
    },
    {
      "bin": "374151",
      "type": "CREDIT",
      "issuer": "AMERICAN EXPRESS",
      "countries": [
        "BE"
      ]
    },
    {
      "bin": "374152",
      "type": "CREDIT",
      "issuer": "AMERICAN EXPRESS",
      "countries": [
        "BE"
      ]
    },
    {
      "bin": "374153",
      "type": "CREDIT",
      "issuer": "AMERICAN EXPRESS",
      "countries": [
        "BE"
      ]
    },
    {
      "bin": "374154",
      "type": "CREDIT",
      "issuer": "AMERICAN EXPRESS",
      "countries": [
        "BE"
      ]
    },
    {
      "bin": "374155",
      "type": "CREDIT",
      "issuer": "AMERICAN EXPRESS",
      "countries": [
        "BE"
      ]
    },
    {
      "bin": "374156",
      "type": "CREDIT",
      "issuer": "AMERICAN EXPRESS",
      "countries": [
        "BE"
      ]
    },
    {
      "bin": "374157",
      "type": "CREDIT",
      "issuer": "AMERICAN EXPRESS",
      "countries": [
        "BE"
      ]
    },
    {
      "bin": "374158",
      "type": "CREDIT",
      "issuer": "AMERICAN EXPRESS",
      "countries": [
        "BE"
      ]
    },
    {
      "bin": "374159",
      "type": "CREDIT",
      "issuer": "AMERICAN EXPRESS",
      "countries": [
        "BE"
      ]
    },
    {
      "bin": "374160",
      "type": "CREDIT",
      "issuer": "AMERICAN EXPRESS",
      "countries": [
        "BE"
      ]
    },
    {
      "bin": "374161",
      "type": "CREDIT",
      "issuer": "AMERICAN EXPRESS",
      "countries": [
        "BE"
      ]
    },
    {
      "bin": "374162",
      "type": "CREDIT",
      "issuer": "AMERICAN EXPRESS",
      "countries": [
        "BE"
      ]
    },
    {
      "bin": "374163",
      "type": "CREDIT",
      "issuer": "AMERICAN EXPRESS",
      "countries": [
        "BE"
      ]
    },
    {
      "bin": "374164",
      "type": "CREDIT",
      "issuer": "AMERICAN EXPRESS",
      "countries": [
        "BE"
      ]
    },
    {
      "bin": "374165",
      "type": "CREDIT",
      "issuer": "AMERICAN EXPRESS",
      "countries": [
        "BE"
      ]
    },
    {
      "bin": "374166",
      "type": "CREDIT",
      "issuer": "AMERICAN EXPRESS",
      "countries": [
        "BE"
      ]
    },
    {
      "bin": "374167",
      "type": "CREDIT",
      "issuer": "AMERICAN EXPRESS",
      "countries": [
        "BE"
      ]
    },
    {
      "bin": "374168",
      "type": "CREDIT",
      "issuer": "AMERICAN EXPRESS",
      "countries": [
        "BE"
      ]
    },
    {
      "bin": "374169",
      "type": "CREDIT",
      "issuer": "AMERICAN EXPRESS",
      "countries": [
        "BE"
      ]
    },
    {
      "bin": "374170",
      "type": "CREDIT",
      "issuer": "AMERICAN EXPRESS",
      "countries": [
        "BE"
      ]
    },
    {
      "bin": "374171",
      "type": "CREDIT",
      "issuer": "AMERICAN EXPRESS",
      "countries": [
        "BE"
      ]
    },
    {
      "bin": "374172",
      "type": "CREDIT",
      "issuer": "AMERICAN EXPRESS",
      "countries": [
        "BE"
      ]
    },
    {
      "bin": "374173",
      "type": "CREDIT",
      "issuer": "AMERICAN EXPRESS",
      "countries": [
        "BE"
      ]
    },
    {
      "bin": "374174",
      "type": "CREDIT",
      "issuer": "AMERICAN EXPRESS",
      "countries": [
        "BE"
      ]
    },
    {
      "bin": "374175",
      "type": "CREDIT",
      "issuer": "AMERICAN EXPRESS",
      "countries": [
        "BE"
      ]
    },
    {
      "bin": "374176",
      "type": "CREDIT",
      "issuer": "AMERICAN EXPRESS",
      "countries": [
        "BE"
      ]
    },
    {
      "bin": "374177",
      "type": "CREDIT",
      "issuer": "AMERICAN EXPRESS",
      "countries": [
        "BE"
      ]
    },
    {
      "bin": "374178",
      "type": "CREDIT",
      "issuer": "AMERICAN EXPRESS",
      "countries": [
        "BE"
      ]
    },
    {
      "bin": "374179",
      "type": "CREDIT",
      "issuer": "AMERICAN EXPRESS",
      "countries": [
        "BE"
      ]
    },
    {
      "bin": "374180",
      "type": "CREDIT",
      "issuer": "AMERICAN EXPRESS",
      "countries": [
        "BE"
      ]
    },
    {
      "bin": "374181",
      "type": "CREDIT",
      "issuer": "KBC",
      "countries": [
        "BE"
      ]
    },
    {
      "bin": "374182",
      "type": "CREDIT",
      "issuer": "AMERICAN EXPRESS",
      "countries": [
        "BE"
      ]
    },
    {
      "bin": "374183",
      "type": "CREDIT",
      "issuer": "AMERICAN EXPRESS",
      "countries": [
        "BE"
      ]
    },
    {
      "bin": "374184",
      "type": "CREDIT",
      "issuer": "AMERICAN EXPRESS",
      "countries": [
        "BE"
      ]
    },
    {
      "bin": "374185",
      "type": "CREDIT",
      "issuer": "AMERICAN EXPRESS",
      "countries": [
        "BE"
      ]
    },
    {
      "bin": "374186",
      "type": "CREDIT",
      "issuer": "AMERICAN EXPRESS",
      "countries": [
        "BE"
      ]
    },
    {
      "bin": "374187",
      "type": "CREDIT",
      "category": "GOLD",
      "issuer": "ING",
      "countries": [
        "BE"
      ]
    },
    {
      "bin": "374188",
      "type": "CREDIT",
      "category": "PLATINUM",
      "issuer": "AMERICAN EXPRESS",
      "countries": [
        "BE"
      ]
    },
    {
      "bin": "374189",
      "type": "CREDIT",
      "issuer": "AMERICAN EXPRESS",
      "countries": [
        "BE"
      ]
    },
    {
      "bin": "374190",
      "type": "CREDIT",
      "issuer": "AMERICAN EXPRESS",
      "countries": [
        "BE"
      ]
    },
    {
      "bin": "374191",
      "type": "CREDIT",
      "issuer": "AMERICAN EXPRESS",
      "countries": [
        "BE"
      ]
    },
    {
      "bin": "374192",
      "type": "CREDIT",
      "issuer": "AMERICAN EXPRESS",
      "countries": [
        "BE"
      ]
    },
    {
      "bin": "374193",
      "type": "CREDIT",
      "issuer": "ING EX BBL BRUSSELS",
      "countries": [
        "BE"
      ]
    },
    {
      "bin": "374194",
      "type": "CREDIT",
      "issuer": "AMERICAN EXPRESS",
      "countries": [
        "BE"
      ]
    },
    {
      "bin": "374195",
      "type": "CREDIT",
      "issuer": "CITIBANK",
      "countries": [
        "BE"
      ]
    },
    {
      "bin": "374196",
      "type": "CREDIT",
      "issuer": "AMERICAN EXPRESS",
      "countries": [
        "BE"
      ]
    },
    {
      "bin": "374197",
      "type": "CREDIT",
      "category": "CORPORATE",
      "issuer": "AMERICAN EXPRESS",
      "countries": [
        "BE"
      ]
    },
    {
      "bin": "374198",
      "type": "CREDIT",
      "issuer": "ING",
      "countries": [
        "BE"
      ]
    },
    {
      "bin": "374199",
      "type": "CREDIT",
      "issuer": "AMERICAN EXPRESS",
      "countries": [
        "BE"
      ]
    },
    {
      "bin": "375984",
      "type": "CREDIT",
      "category": "GREEN",
      "issuer": "BNP PARISBAS FORTIS",
      "countries": [
        "BE"
      ]
    },
    {
      "bin": "375987",
      "type": "CREDIT",
      "category": "GOLD",
      "issuer": "BNP PARISBAS FORTIS",
      "countries": [
        "BE"
      ]
    }
  ]
}
